{
  "parent": "items:air",
  "display": {
    "icon": {
      "id": "minecraft:cod"
    },
    "title": "Cod",
    "description": "Obtain Cod",
    "frame": "task",
    "show_toast": true,
    "announce_to_chat": true,
    "hidden": false
  },
  "criteria": {
    "cod": {
      "trigger": "minecraft:inventory_changed",
      "conditions": {
        "items": [
          {
            "items": "minecraft:cod"
          }
        ]
      }
    }
  },
  "requirements": [
    [
      "cod"
    ]
  ],
  "sends_telemetry_event": true
}
